lasha_chipashvili/__init__.py
lasha_chipashvili/lasha_chipashvili.py
lasha_chipashvili_package-0.1.dist-info/licenses/LICENSE
lasha_chipashvili_package-0.1.dist-info/METADATA
lasha_chipashvili_package-0.1.dist-info/WHEEL
lasha_chipashvili_package-0.1.dist-info/top_level.txt
lasha_chipashvili_package-0.1.dist-info/RECORD
